retrochem_launcher.py
RetroChem/Retrochem.py
RetroChem/__init__.py
RetroChem/Data/__init__.py
RetroChem/Data/combined_data.csv
RetroChem/Data/reaction_templates_50k_test.csv
RetroChem/Data/reaction_templates_50k_train.csv
RetroChem/Data/reaction_templates_50k_valid.csv
RetroChem/Model/__init__.py
RetroChem/Model/label_encoder.pkl
RetroChem/Model/mlp_classifier_model.pkl
RetroChem/Model/scaler.pkl
RetroChem/Package_functions/Interface_functions.py
RetroChem/Package_functions/Model_training_functions.py
RetroChem/Package_functions/__init__.py
retrochem-0.2.0.dist-info/licenses/LICENSE
retrochem-0.2.0.dist-info/METADATA
retrochem-0.2.0.dist-info/WHEEL
retrochem-0.2.0.dist-info/entry_points.txt
retrochem-0.2.0.dist-info/top_level.txt
retrochem-0.2.0.dist-info/RECORD
