Metadata-Version: 2.4
Name: RetroChem
Version: 0.2.0
Summary: Retrosynthesis, visualization and machine learning tools
Author: Jacques Grandjean, Noah Paganuzzi, Florian Follet, Giulio Garotti
Requires-Python: >=3.10
License-File: LICENSE
Requires-Dist: streamlit
Requires-Dist: pandas
Requires-Dist: numpy==2.2.6
Requires-Dist: joblib
Requires-Dist: rdkit
Requires-Dist: scikit-learn
Requires-Dist: matplotlib
Requires-Dist: pillow
Requires-Dist: streamlit-ketcher
Dynamic: author
Dynamic: description
Dynamic: description-content-type
Dynamic: license-file
Dynamic: requires-dist
Dynamic: requires-python
Dynamic: summary
